xensegripper/__compile__.cpython-39-x86_64-linux-gnu.so
xensegripper/__init__.py
xensegripper/__init__.pyi
xensegripper/__pycache__/__init__.cpython-39.opt-1.pyc
xensegripper/__pycache__/__init__.cpython-39.pyc
xensegripper/controller/__init__.py
xensegripper/controller/__pycache__/__init__.cpython-39.opt-1.pyc
xensegripper/controller/__pycache__/__init__.cpython-39.pyc
xensegripper/node/__init__.py
xensegripper/node/__pycache__/__init__.cpython-39.opt-1.pyc
xensegripper/node/__pycache__/__init__.cpython-39.pyc
xensegripper-1.1.8.dist-info/METADATA
xensegripper-1.1.8.dist-info/WHEEL
xensegripper-1.1.8.dist-info/entry_points.txt
xensegripper-1.1.8.dist-info/top_level.txt
xensegripper-1.1.8.dist-info/RECORD
