Metadata-Version: 2.4
Name: xensegripper
Version: 1.1.8
Summary: xense gripper SDK for everything supported
Author: Hongzhan Yu
Author-email: yuhongzhan@xenserobotics.com
Classifier: Programming Language :: Python :: 3
Classifier: License :: OSI Approved :: MIT License
Classifier: Operating System :: OS Independent
Requires-Python: >=3.9
Requires-Dist: pyserial
Requires-Dist: xensesdk>=1.6.3
Dynamic: author
Dynamic: author-email
Dynamic: classifier
Dynamic: requires-dist
Dynamic: requires-python
Dynamic: summary
